lightningflow/__init__.py
lightningflow/core.py
lightningflow/environment.py
lightningflow/exceptions.py
lightningflow/funcs.py
lightningflow/parameters.py
lightningflow/utils.py
lightningflow/validators.py
lightningflow-0.1.4.dist-info/WHEEL
lightningflow-0.1.4.dist-info/METADATA
lightningflow-0.1.4.dist-info/RECORD
